<?xml version="1.0" encoding="UTF-8"?>
<metadata xml:lang="nl"><Esri><CreaDate>20181029</CreaDate><CreaTime>09003900</CreaTime><ArcGISFormat>1.0</ArcGISFormat><SyncOnce>TRUE</SyncOnce><DataProperties><lineage><Process Name="Add Field" ToolSource="c:\program files (x86)\arcgis\desktop10.5\ArcToolbox\Toolboxes\Data Management Tools.tbx\AddField" Date="20181029" Time="090039">AddField "Voorlopig referentiebestand gemeentegrenzen - Arrondissement - gegeneraliseerd 100m" LENGTE DOUBLE # # # # NULLABLE NON_REQUIRED #</Process><Process Name="Calculate Field" ToolSource="c:\program files (x86)\arcgis\desktop10.5\ArcToolbox\Toolboxes\Data Management Tools.tbx\CalculateField" Date="20181029" Time="090040">CalculateField "Voorlopig referentiebestand gemeentegrenzen - Arrondissement - gegeneraliseerd 100m" LENGTE [SHAPE_Leng] VB #</Process><Process Name="Add Field (2)" ToolSource="c:\program files (x86)\arcgis\desktop10.5\ArcToolbox\Toolboxes\Data Management Tools.tbx\AddField" Date="20181029" Time="090040">AddField "Voorlopig referentiebestand gemeentegrenzen - Arrondissement - gegeneraliseerd 100m" OPPERVL DOUBLE # # # # NULLABLE NON_REQUIRED #</Process><Process Name="Calculate Field (2)" ToolSource="c:\program files (x86)\arcgis\desktop10.5\ArcToolbox\Toolboxes\Data Management Tools.tbx\CalculateField" Date="20181029" Time="090040">CalculateField "Voorlopig referentiebestand gemeentegrenzen - Arrondissement - gegeneraliseerd 100m" OPPERVL [SHAPE_Area] VB #</Process><Process Name="Delete Field (2)" ToolSource="c:\program files (x86)\arcgis\desktop10.5\ArcToolbox\Toolboxes\Data Management Tools.tbx\DeleteField" Date="20181029" Time="090041">DeleteField "Voorlopig referentiebestand gemeentegrenzen - Arrondissement - gegeneraliseerd 100m" SHAPE_Leng;SHAPE_Area</Process></lineage></DataProperties></Esri></metadata>
